aitviewer/__init__.py
aitviewer/aitvconfig.yaml
aitviewer/configuration.py
aitviewer/headless.py
aitviewer/renderer.py
aitviewer/server.py
aitviewer/shaders.py
aitviewer/viewer.py
aitviewer/models/__init__.py
aitviewer/models/smpl.py
aitviewer/models/star.py
aitviewer/models/supr.py
aitviewer/remote/__init__.py
aitviewer/remote/message.py
aitviewer/remote/node.py
aitviewer/remote/viewer.py
aitviewer/remote/renderables/__init__.py
aitviewer/remote/renderables/arrows.py
aitviewer/remote/renderables/lines.py
aitviewer/remote/renderables/meshes.py
aitviewer/remote/renderables/rigid_bodies.py
aitviewer/remote/renderables/smpl.py
aitviewer/remote/renderables/spheres.py
aitviewer/renderables/__init__.py
aitviewer/renderables/arrows.py
aitviewer/renderables/billboard.py
aitviewer/renderables/bounding_boxes.py
aitviewer/renderables/coordinate_system.py
aitviewer/renderables/gaussian_splats.py
aitviewer/renderables/lines.py
aitviewer/renderables/meshes.py
aitviewer/renderables/multi_view_system.py
aitviewer/renderables/plane.py
aitviewer/renderables/point_clouds.py
aitviewer/renderables/rigid_bodies.py
aitviewer/renderables/sdf.py
aitviewer/renderables/skeletons.py
aitviewer/renderables/smpl.py
aitviewer/renderables/spheres.py
aitviewer/renderables/star.py
aitviewer/renderables/supr.py
aitviewer/renderables/volume.py
aitviewer/resources/fonts/Custom.sfd
aitviewer/resources/fonts/Custom.ttf
aitviewer/scene/__init__.py
aitviewer/scene/camera.py
aitviewer/scene/camera_utils.py
aitviewer/scene/light.py
aitviewer/scene/material.py
aitviewer/scene/node.py
aitviewer/scene/scene.py
aitviewer/shaders/chessboard.glsl
aitviewer/shaders/clipping.glsl
aitviewer/shaders/cylinder.glsl
aitviewer/shaders/directional_lights.glsl
aitviewer/shaders/lines_instanced.vs.glsl
aitviewer/shaders/lines_instanced_positions.vs.glsl
aitviewer/shaders/lit_with_edges.glsl
aitviewer/shaders/mesh_positions.vs.glsl
aitviewer/shaders/screen_texture.glsl
aitviewer/shaders/simple_unlit.glsl
aitviewer-1.13.0.dist-info/LICENSE
aitviewer-1.13.0.dist-info/METADATA
aitviewer-1.13.0.dist-info/WHEEL
aitviewer-1.13.0.dist-info/top_level.txt
aitviewer-1.13.0.dist-info/RECORD
