Metadata-Version: 2.1
Name: aitviewer
Version: 1.13.0
Summary: Viewing and rendering of sequences of 3D data.
Home-page: https://github.com/eth-ait/aitviewer
Author: Manuel Kaufmann, Velko Vechev, Dario Mylonopoulos
Project-URL: Documentation, https://eth-ait.github.io/aitviewer/
Project-URL: Source, https://github.com/eth-ait/aitviewer
Project-URL: Bug Tracker, https://github.com/eth-ait/aitviewer/issues
Keywords: viewer,moderngl,machine learning,sequences,smpl,computer graphics,computer vision,3D,meshes,visualization
Platform: any
Requires-Python: >=3.7,<3.11
License-File: LICENSE
Requires-Dist: torch (>=1.6.0)
Requires-Dist: numpy (<2,>=1.18)
Requires-Dist: opencv-contrib-python-headless (>=4.5.1.48)
Requires-Dist: smplx
Requires-Dist: moderngl-window (>=2.4.3)
Requires-Dist: moderngl (<6,>=5.8.2)
Requires-Dist: imgui (==2.0.0)
Requires-Dist: tqdm (>=4.60.0)
Requires-Dist: trimesh (<4,>=3.9.15)
Requires-Dist: scipy (>=1.5.2)
Requires-Dist: omegaconf (>=2.1.1)
Requires-Dist: roma (>=1.2.3)
Requires-Dist: joblib
Requires-Dist: scikit-image (>=0.9.0)
Requires-Dist: scikit-video
Requires-Dist: Pillow
Requires-Dist: websockets
Requires-Dist: usd-core (>=23.5)
Requires-Dist: PyQt5 (>=5.15.4)
